mst/semester/__init__.py
mst/semester/semester.py
mst_semester-0.1.2.dist-info/METADATA
mst_semester-0.1.2.dist-info/WHEEL
mst_semester-0.1.2.dist-info/top_level.txt
mst_semester-0.1.2.dist-info/RECORD
