Metadata-Version: 2.1
Name: mst-semester
Version: 0.1.2
Summary: mst-semester contains methods for working with school terms.
Author-email: Missouri University of Science and Technology - Information Technology <it-ai@mst.edu>
Requires-Python: >=3.11
Requires-Dist: requests
Requires-Dist: mst-core
